ssh_connection_manager-0.1.0.dist-info/licenses/LICENSE
sshm/__init__.py
sshm/cli.py
sshm/data.py
sshm/utils.py
ssh_connection_manager-0.1.0.dist-info/METADATA
ssh_connection_manager-0.1.0.dist-info/WHEEL
ssh_connection_manager-0.1.0.dist-info/entry_points.txt
ssh_connection_manager-0.1.0.dist-info/top_level.txt
ssh_connection_manager-0.1.0.dist-info/RECORD
