Metadata-Version: 2.4
Name: ssh-connection-manager
Version: 0.1.0
Summary: simple ssh manager inspired by zoxide
Author: jhell
License:                     GNU GENERAL PUBLIC LICENSE
Keywords: ssh
Requires-Python: >=3.9
License-File: LICENSE
Requires-Dist: build==1.3.0
Requires-Dist: click==8.2.1
Requires-Dist: fuzzyfinder==2.3.0
Requires-Dist: markdown-it-py==4.0.0
Requires-Dist: mdurl==0.1.2
Requires-Dist: packaging==25.0
Requires-Dist: Pygments==2.19.2
Requires-Dist: pyproject_hooks==1.2.0
Requires-Dist: rich==14.1.0
Requires-Dist: shellingham==1.5.4
Requires-Dist: SQLAlchemy==2.0.43
Requires-Dist: typer==0.17.3
Requires-Dist: typing_extensions==4.15.0
Requires-Dist: platformdirs==4.4.0
Dynamic: license-file
